myplant/__init__.py
myplant/admin.py
myplant/apps.py
myplant/models.py
myplant/tests.py
myplant/views.py
myplant/migrations/__init__.py
django_myplant-0.0.1.dist-info/LICENSE
django_myplant-0.0.1.dist-info/METADATA
django_myplant-0.0.1.dist-info/WHEEL
django_myplant-0.0.1.dist-info/top_level.txt
django_myplant-0.0.1.dist-info/RECORD
