Metadata-Version: 2.1
Name: django-myplant
Version: 0.0.1
Summary: this is for compal plants
Home-page: UNKNOWN
Author: Manny_Zheng
Author-email: imzhengk@qq.com
License: UNKNOWN
Platform: UNKNOWN
Classifier: Programming Language :: Python :: 3
Classifier: License :: OSI Approved :: MIT License
Classifier: Operating System :: OS Independent
